kmer_counting/__init__.py
kmer_counting/kmer_counting_loop.py
kmer_counting-0.1.0.dist-info/LICENSE
kmer_counting-0.1.0.dist-info/METADATA
kmer_counting-0.1.0.dist-info/WHEEL
kmer_counting-0.1.0.dist-info/entry_points.txt
kmer_counting-0.1.0.dist-info/top_level.txt
kmer_counting-0.1.0.dist-info/RECORD
