Metadata-Version: 2.1
Name: kmer_counting
Version: 0.1.0
Summary: kmer counting from sequencing fastq.gz file
Home-page: https://github.com/QiangSu/GaussF
Author: Qiang Su
Author-email: qiang_su@hotmail.com
Classifier: Programming Language :: Python :: 3
Classifier: License :: OSI Approved :: MIT License
Classifier: Operating System :: OS Independent
Requires-Python: >=3.6
License-File: LICENSE
